<?xml version="1.0" encoding="UTF-8"?>
<QBXML>
  <QBXMLMsgsRs>
    <CustomerAddRs requestID="2" statusCode="0" statusSeverity="Info" statusMessage="Status OK">
      <CustomerRet>
        <ListID>8000000C-1412613002</ListID>
        <TimeCreated>2014-10-06T13:30:02-02:00</TimeCreated>
        <TimeModified>2014-10-06T13:30:02-02:00</TimeModified>
        <EditSequence>1412613002</EditSequence>
        <Name>Eric</Name>
        <FullName>Eric</FullName>
        <IsActive>true</IsActive>
        <Sublevel>0</Sublevel>
        <Balance>0.00</Balance>
        <TotalBalance>0.00</TotalBalance>
        <JobStatus>None</JobStatus>
      </CustomerRet>
    </CustomerAddRs>
  </QBXMLMsgsRs>
</QBXML>